{
  "mock": {
    "islocal": false,
    "mockApiEndpoint": "https://okta-apis.azurewebsites.net"
  },
  "okta": {
    "baseDomain": "https://dev-952251.okta.com",
    "issuer": "https://dev-952251.okta.com/oauth2/default",
    "redirectUri": "https://jssokta/implicitcallback",
    "clientId": "0oafzoycnHmt4Fjbd4x6",
    "pkce": true,
    "scopes": ["openid", "profile", "email"],
    "portalRoute": "/profile",
    "loginRoute": "/login"
  },
  "debug": {
    "showApiErrors": false,
    "showDebugJson": false
  }
}
